CHANGES.txt
COPYRIGHT.txt
LICENSE.txt
README.txt
bootstrap.py
buildout.cfg
setup.cfg
setup.py
Products/__init__.py
Products.CAS4PAS.egg-info/PKG-INFO
Products.CAS4PAS.egg-info/SOURCES.txt
Products.CAS4PAS.egg-info/dependency_links.txt
Products.CAS4PAS.egg-info/entry_points.txt
Products.CAS4PAS.egg-info/namespace_packages.txt
Products.CAS4PAS.egg-info/not-zip-safe
Products.CAS4PAS.egg-info/requires.txt
Products.CAS4PAS.egg-info/top_level.txt
Products/CAS4PAS/CASAuthHelper.py
Products/CAS4PAS/CASXMLResponseParser.py
Products/CAS4PAS/__init__.py
Products/CAS4PAS/configure.zcml
Products/CAS4PAS/zmi/CASAuthHelper.gif
Products/CAS4PAS/zmi/addCASAuthHelperForm.zpt