Metadata-Version: 1.0
Name: Products.CAS4PAS
Version: 2.1.2
Summary: A PAS plugin that authenticates users against a CAS (Central Authentication Service) server.
Home-page: http://pypi.python.org/pypi/Products.CAS4PAS
Author: Lennart Regebro/Zope community
Author-email: product-developers@lists.plone.org
License: ZPL
Keywords: zope PAS
Platform: UNKNOWN
Classifier: Framework :: Zope2
Classifier: Programming Language :: Python
Classifier: Topic :: Software Development :: Libraries :: Python Modules
